alita_mcp/__init__.py
alita_mcp/config.py
alita_mcp/main.py
alita_mcp/tray.py
alita_mcp/clients/__init__.py
alita_mcp/clients/alita.py
alita_mcp/commands/__init__.py
alita_mcp/commands/bootstrap_servers.py
alita_mcp/commands/run_servers.py
alita_mcp/icons/__init__.py
alita_mcp/icons/logo.png
alita_mcp/icons/logo64x64.png
alita_mcp/server/__init__.py
alita_mcp/server/mcp.py
alita_mcp/utils/__init__.py
alita_mcp/utils/menu.py
alita_mcp/utils/name.py
alita_mcp/utils/package_updates.py
alita_mcp/utils/server_controller.py
alita_mcp/utils/session_manager.py
alita_mcp/utils/sio.py
alita_mcp-0.1.33.dist-info/licenses/LICENSE
alita_mcp-0.1.33.dist-info/METADATA
alita_mcp-0.1.33.dist-info/WHEEL
alita_mcp-0.1.33.dist-info/entry_points.txt
alita_mcp-0.1.33.dist-info/top_level.txt
alita_mcp-0.1.33.dist-info/RECORD
