Metadata-Version: 2.4
Name: alita-mcp
Version: 0.1.33
Summary: ELITEA MCP Client
Author-email: Artem Rozumenko <artyom.rozumenko@gmail.com>
Maintainer-email: Aliaksei Breilian <Aliaksei_Breilian@epam.com>, Mikalai Biazruchka <Mikalai_Biazruchka@epam.com>
License-Expression: Apache-2.0
Project-URL: Homepage, https://github.com/ProjectAlita/alita-mcp-client
Project-URL: Issues, https://github.com/ProjectAlita/alita-mcp-client/issues
Project-URL: Documentation, https://github.com/ProjectAlita/alita-mcp-client#readme
Project-URL: Repository, https://github.com/ProjectAlita/alita-mcp-client.git
Keywords: client,mcp,alita
Classifier: Development Status :: 4 - Beta
Classifier: Intended Audience :: Developers
Classifier: Programming Language :: Python :: 3
Classifier: Programming Language :: Python :: 3.10
Classifier: Programming Language :: Python :: 3.11
Classifier: Programming Language :: Python :: 3.12
Requires-Python: >=3.10
License-File: LICENSE
Requires-Dist: appdirs>=1.4.4
Requires-Dist: requests~=2.32.3
Requires-Dist: pytest~=8.3.5
Requires-Dist: mcp==1.12.4
Requires-Dist: pydantic<3.0,>=2.0
Requires-Dist: python-dotenv>=1.0.0
Requires-Dist: python-socketio[client]~=5.13.0
Requires-Dist: websocket-client~=1.8.0
Requires-Dist: pystray>=0.19.0
Requires-Dist: pillow>=8.0.0
Requires-Dist: pyobjc-framework-Cocoa>=8.0; sys_platform == "darwin"
Dynamic: license-file
